Metadata-Version: 2.1
Name: ammarpyasa
Version: 0.0
Summary: Calculate and visuallize, Gaussian, Binomial and Normal distributions
Author-email: sjahnaviprasad@gmail.com
